{"__v":0,"_id":{"$oid":"55472578221398c41d1e7a4a"},"brand":"Samsung","comments":[],"description":"Màn hình: 5.1\", 1440 x 2560 pixels.\nCPU: Exynos 7420, 8 nhân, 4x1.5GHz Cortex-A53 \u0026 4x2.1 GHz Cortex-A57.\nRAM:3 GB.\nHệ điều hành:\u0009Android 5.0 (Lollipop)\nCamera: chính\u000916.0 MP, Quay phim 4K 2160p@30fps.\nCamera phụ:\u00095.0 MP\nBộ nhớ trong:\u000932 GB\nDung lượng pin:\u00092550 mAh","id_category":"554348d3d4e95a400d2a6470","image":"bf20d95aaff59a607a518afc3aca3bfb.jpg","name":"Samsung Galaxy S6","prices":[],"tag":"s6, samsung"}
{"__v":0,"_id":{"$oid":"55472833221398c41d1e7a4b"},"brand":"Nikon","comments":[],"description":"Cảm biến CMOS Fullframe 12.2 Megapixels. Bộ xử lý ảnh thế hệ mới EXPEED. Độ nhạy sáng ISO lớn nhất lên tới 26500. Tốc độ chụp liên tục 5 hình/giây. Hệ thống lấy nét tự động 51 điểm Multi-CAM 3500FX. Hệ thống đo sáng 3D Color Matrix Metering thế hệ II. Màn hình 3\" với hai chức năng Liveview. Thân máy hợp kim Magnesium","id_category":"554358d59ee855c009f933cb","image":"f6d9b03743f5689edee998afb3faf262.jpg","name":"Nikon D700","prices":[],"tag":"nikon, d700"}
{"__v":0,"_id":{"$oid":"554729c7221398c41d1e7a4c"},"brand":"Toshiba","comments":[],"description":"Tính năng: Tivi LED\nMàn hình: 40 inch\nĐộ phân giải: Full HD\nKết nối: USB, HDMI\nTần số quét: AMR 200 Hz\nCông suất loa: 20W","id_category":"5543596b9ee855c009f933cd","image":"20ebce286da70c1d465b0a7861e0f914.jpg","name":"Tivi LED Toshiba 40L2450 40inch","prices":[],"tag":"tivi, led, toshiba, 40inch"}
{"__v":0,"_id":{"$oid":"55472a57221398c41d1e7a4d"},"brand":"Apple","comments":[],"description":"Hệ điều hành: Mountain Lion OS 10.8\nĐộ lớn màn hình: 11.6\" LED Webcam\nBộ vi xử lý: CPU Intel Core i5 (1.4Ghz;3MB)","id_category":"554359a79ee855c009f933ce","image":"ba805c0d6b0761ba4b762172c4ba420b.jpg","name":"Laptop Macbook Air 2014 MD711ZP 11.6inch (Bạc)","prices":[],"tag":"macbookair, apple"}
{"__v":0,"_id":{"$oid":"55472ad0221398c41d1e7a4e"},"brand":"LG","comments":[],"description":"Mã sản phẩm: GN-L222BS\nHãng sản xuất: LG\nSản xuất tại: Indonesia\nBảo hành chính hãng: 12 tháng\nTình trạng: Hàng mới 100% nguyên đai - nguyên kiện\nHình thức vận chuyển: Miễn phí nội thành, hỗ trợ giao hàng toàn quốc.","id_category":"554358789ee855c009f933ca","image":"3ed4ba005290f87724e9cc9ccfb42c27.jpg","name":"Tủ Lạnh LG GN-L222BS","prices":[],"tag":"lg, tulanh"}
{"__v":0,"_id":{"$oid":"554e09f877fe171c16b4c1fc"},"brand":"Samsung","comments":[],"description":"Máy đẹp","id_category":"554348d3d4e95a400d2a6470","image":"d623c5d1c9fe07c9236647cf025a3ed9.jpg","name":"Samsung Galaxy Y","prices":[],"tag":"galaxy"}
